tropicalia/__init__.py
tropicalia/client.py
tropicalia/core/__init__.py
tropicalia/core/api_error.py
tropicalia/core/client_wrapper.py
tropicalia/core/datetime_utils.py
tropicalia/core/file.py
tropicalia/core/force_multipart.py
tropicalia/core/http_client.py
tropicalia/core/http_response.py
tropicalia/core/http_sse/__init__.py
tropicalia/core/http_sse/_api.py
tropicalia/core/http_sse/_decoders.py
tropicalia/core/http_sse/_exceptions.py
tropicalia/core/http_sse/_models.py
tropicalia/core/jsonable_encoder.py
tropicalia/core/pydantic_utilities.py
tropicalia/core/query_encoder.py
tropicalia/core/remove_none_from_dict.py
tropicalia/core/request_options.py
tropicalia/core/serialization.py
tropicalia/environment.py
tropicalia/projects/__init__.py
tropicalia/projects/client.py
tropicalia/projects/raw_client.py
tropicalia/py.typed
tropicalia/raw_client.py
tropicalia/types/__init__.py
tropicalia/types/document.py
tropicalia/types/document_delete_response.py
tropicalia/types/document_status.py
tropicalia/types/project.py
tropicalia/types/project_delete_response.py
tropicalia/types/retrieval_content.py
tropicalia/types/retrieval_metadata.py
tropicalia/types/retrieval_metadata_type.py
tropicalia/types/retrieval_strategy.py
tropicalia/types/search_response.py
tropicalia/types/upload_response.py
tropicalia/upload/__init__.py
tropicalia/upload/client.py
tropicalia/upload/raw_client.py
tropicalia/version.py
tropicalia-0.1.0.dist-info/METADATA
tropicalia-0.1.0.dist-info/WHEEL
tropicalia-0.1.0.dist-info/RECORD
